csv_json/__init__.py
csv_json/csv_to_json.py
csv_json/csvjson.py
csv_json/json_to_csv.py
csv_json-1.0.2.dist-info/LICENSE.txt
csv_json-1.0.2.dist-info/METADATA
csv_json-1.0.2.dist-info/WHEEL
csv_json-1.0.2.dist-info/top_level.txt
csv_json-1.0.2.dist-info/RECORD
