Metadata-Version: 2.1
Name: csv-json
Version: 1.0.2
Summary: A package to convert csv files to json and vice-versa
Home-page: https://github.com/TeamCoders02/csv_json
Author: Daniel, Harish
Author-email: teamcoders21@gmail.com
License: UNKNOWN
Platform: UNKNOWN
Classifier: Programming Language :: Python :: 3
Classifier: License :: OSI Approved :: MIT License
Classifier: Operating System :: OS Independent
Requires-Python: >=3.6
